{
  "axes": [
    {
      "scale": "x",
      "title": "Time",
      "type": "x"
    },
    {
      "scale": "y",
      "title": "Freq",
      "type": "y"
    }
  ],
  "data": [
    {
      "name": "table",
      "values": [
        {
          "col": "data",
          "idx": 1499618217000,
          "val": 1
        },
        {
          "col": "data",
          "idx": 1499619082000,
          "val": 1
        },
        {
          "col": "data",
          "idx": 1499619614000,
          "val": 1
        },
        {
          "col": "data",
          "idx": 1499620515000,
          "val": 1
        },
        {
          "col": "data",
          "idx": 1499620866000,
          "val": 1
        },
        {
          "col": "data",
          "idx": 1499620921000,
          "val": 1
        },
        {
          "col": "data",
          "idx": 1499620989000,
          "val": 1
        },
        {
          "col": "data",
          "idx": 1499621427000,
          "val": 1
        },
        {
          "col": "data",
          "idx": 1499621446000,
          "val": 1
        },
        {
          "col": "data",
          "idx": 1499621525000,
          "val": 1
        },
        {
          "col": "data",
          "idx": 1499621946000,
          "val": 1
        },
        {
          "col": "data",
          "idx": 1499622007000,
          "val": 1
        },
        {
          "col": "data",
          "idx": 1499622319000,
          "val": 1
        },
        {
          "col": "data",
          "idx": 1499622540000,
          "val": 1
        },
        {
          "col": "data",
          "idx": 1499623216000,
          "val": 1
        },
        {
          "col": "data",
          "idx": 1499623415000,
          "val": 1
        },
        {
          "col": "data",
          "idx": 1499623506000,
          "val": 1
        },
        {
          "col": "data",
          "idx": 1499623883000,
          "val": 1
        },
        {
          "col": "data",
          "idx": 1499624055000,
          "val": 1
        },
        {
          "col": "data",
          "idx": 1499625426000,
          "val": 1
        },
        {
          "col": "data",
          "idx": 1499625567000,
          "val": 1
        },
        {
          "col": "data",
          "idx": 1499625843000,
          "val": 1
        },
        {
          "col": "data",
          "idx": 1499625884000,
          "val": 1
        },
        {
          "col": "data",
          "idx": 1499625903000,
          "val": 1
        },
        {
          "col": "data",
          "idx": 1499626630000,
          "val": 1
        },
        {
          "col": "data",
          "idx": 1499628321000,
          "val": 1
        },
        {
          "col": "data",
          "idx": 1499628472000,
          "val": 1
        },
        {
          "col": "data",
          "idx": 1499628638000,
          "val": 1
        },
        {
          "col": "data",
          "idx": 1499629036000,
          "val": 1
        },
        {
          "col": "data",
          "idx": 1499629813000,
          "val": 1
        },
        {
          "col": "data",
          "idx": 1499630868000,
          "val": 1
        },
        {
          "col": "data",
          "idx": 1499631307000,
          "val": 1
        },
        {
          "col": "data",
          "idx": 1499631320000,
          "val": 1
        },
        {
          "col": "data",
          "idx": 1499631428000,
          "val": 1
        },
        {
          "col": "data",
          "idx": 1499631495000,
          "val": 1
        },
        {
          "col": "data",
          "idx": 1499631985000,
          "val": 1
        },
        {
          "col": "data",
          "idx": 1499632201000,
          "val": 1
        },
        {
          "col": "data",
          "idx": 1499632214000,
          "val": 1
        },
        {
          "col": "data",
          "idx": 1499632700000,
          "val": 1
        },
        {
          "col": "data",
          "idx": 1499632828000,
          "val": 1
        },
        {
          "col": "data",
          "idx": 1499633135000,
          "val": 1
        },
        {
          "col": "data",
          "idx": 1499633272000,
          "val": 1
        },
        {
          "col": "data",
          "idx": 1499633576000,
          "val": 1
        },
        {
          "col": "data",
          "idx": 1499633883000,
          "val": 1
        },
        {
          "col": "data",
          "idx": 1499633886000,
          "val": 1
        },
        {
          "col": "data",
          "idx": 1499634001000,
          "val": 1
        },
        {
          "col": "data",
          "idx": 1499634046000,
          "val": 1
        },
        {
          "col": "data",
          "idx": 1499634130000,
          "val": 1
        },
        {
          "col": "data",
          "idx": 1499634456000,
          "val": 1
        },
        {
          "col": "data",
          "idx": 1499634614000,
          "val": 1
        },
        {
          "col": "data",
          "idx": 1499634671000,
          "val": 1
        },
        {
          "col": "data",
          "idx": 1499634757000,
          "val": 1
        },
        {
          "col": "data",
          "idx": 1499635530000,
          "val": 1
        },
        {
          "col": "data",
          "idx": 1499635600000,
          "val": 1
        },
        {
          "col": "data",
          "idx": 1499636150000,
          "val": 1
        },
        {
          "col": "data",
          "idx": 1499636369000,
          "val": 1
        },
        {
          "col": "data",
          "idx": 1499636410000,
          "val": 1
        },
        {
          "col": "data",
          "idx": 1499636582000,
          "val": 1
        },
        {
          "col": "data",
          "idx": 1499636785000,
          "val": 1
        },
        {
          "col": "data",
          "idx": 1499636800000,
          "val": 1
        },
        {
          "col": "data",
          "idx": 1499636872000,
          "val": 1
        },
        {
          "col": "data",
          "idx": 1499637388000,
          "val": 1
        },
        {
          "col": "data",
          "idx": 1499637394000,
          "val": 1
        },
        {
          "col": "data",
          "idx": 1499637572000,
          "val": 1
        },
        {
          "col": "data",
          "idx": 1499637935000,
          "val": 1
        },
        {
          "col": "data",
          "idx": 1499638128000,
          "val": 1
        },
        {
          "col": "data",
          "idx": 1499638361000,
          "val": 1
        },
        {
          "col": "data",
          "idx": 1499638435000,
          "val": 1
        },
        {
          "col": "data",
          "idx": 1499638499000,
          "val": 1
        },
        {
          "col": "data",
          "idx": 1499638512000,
          "val": 1
        },
        {
          "col": "data",
          "idx": 1499639033000,
          "val": 1
        },
        {
          "col": "data",
          "idx": 1499639683000,
          "val": 1
        },
        {
          "col": "data",
          "idx": 1499640550000,
          "val": 1
        },
        {
          "col": "data",
          "idx": 1499640684000,
          "val": 1
        },
        {
          "col": "data",
          "idx": 1499640714000,
          "val": 1
        },
        {
          "col": "data",
          "idx": 1499640890000,
          "val": 1
        },
        {
          "col": "data",
          "idx": 1499640930000,
          "val": 1
        },
        {
          "col": "data",
          "idx": 1499640959000,
          "val": 1
        },
        {
          "col": "data",
          "idx": 1499641039000,
          "val": 1
        },
        {
          "col": "data",
          "idx": 1499641214000,
          "val": 1
        },
        {
          "col": "data",
          "idx": 1499641217000,
          "val": 1
        },
        {
          "col": "data",
          "idx": 1499641253000,
          "val": 1
        },
        {
          "col": "data",
          "idx": 1499641510000,
          "val": 1
        },
        {
          "col": "data",
          "idx": 1499641691000,
          "val": 1
        },
        {
          "col": "data",
          "idx": 1499642111000,
          "val": 1
        },
        {
          "col": "data",
          "idx": 1499642130000,
          "val": 1
        },
        {
          "col": "data",
          "idx": 1499642181000,
          "val": 1
        },
        {
          "col": "data",
          "idx": 1499642626000,
          "val": 1
        },
        {
          "col": "data",
          "idx": 1499642736000,
          "val": 1
        },
        {
          "col": "data",
          "idx": 1499643027000,
          "val": 1
        },
        {
          "col": "data",
          "idx": 1499643060000,
          "val": 1
        },
        {
          "col": "data",
          "idx": 1499643314000,
          "val": 1
        },
        {
          "col": "data",
          "idx": 1499643455000,
          "val": 1
        },
        {
          "col": "data",
          "idx": 1499643773000,
          "val": 1
        },
        {
          "col": "data",
          "idx": 1499643918000,
          "val": 1
        },
        {
          "col": "data",
          "idx": 1499644037000,
          "val": 1
        },
        {
          "col": "data",
          "idx": 1499644464000,
          "val": 1
        },
        {
          "col": "data",
          "idx": 1499644551000,
          "val": 1
        },
        {
          "col": "data",
          "idx": 1499644753000,
          "val": 1
        },
        {
          "col": "data",
          "idx": 1499644755000,
          "val": 1
        },
        {
          "col": "data",
          "idx": 1499644807000,
          "val": 1
        },
        {
          "col": "data",
          "idx": 1499644816000,
          "val": 1
        },
        {
          "col": "data",
          "idx": 1499644845000,
          "val": 1
        },
        {
          "col": "data",
          "idx": 1499644932000,
          "val": 1
        },
        {
          "col": "data",
          "idx": 1499645041000,
          "val": 1
        },
        {
          "col": "data",
          "idx": 1499645106000,
          "val": 1
        },
        {
          "col": "data",
          "idx": 1499645125000,
          "val": 1
        },
        {
          "col": "data",
          "idx": 1499645141000,
          "val": 1
        },
        {
          "col": "data",
          "idx": 1499645198000,
          "val": 1
        },
        {
          "col": "data",
          "idx": 1499645242000,
          "val": 1
        },
        {
          "col": "data",
          "idx": 1499645281000,
          "val": 1
        },
        {
          "col": "data",
          "idx": 1499645426000,
          "val": 1
        },
        {
          "col": "data",
          "idx": 1499645500000,
          "val": 1
        },
        {
          "col": "data",
          "idx": 1499645524000,
          "val": 1
        },
        {
          "col": "data",
          "idx": 1499645555000,
          "val": 1
        },
        {
          "col": "data",
          "idx": 1499645591000,
          "val": 1
        },
        {
          "col": "data",
          "idx": 1499645612000,
          "val": 1
        },
        {
          "col": "data",
          "idx": 1499645654000,
          "val": 1
        },
        {
          "col": "data",
          "idx": 1499645671000,
          "val": 1
        },
        {
          "col": "data",
          "idx": 1499645675000,
          "val": 1
        },
        {
          "col": "data",
          "idx": 1499645708000,
          "val": 1
        },
        {
          "col": "data",
          "idx": 1499645727000,
          "val": 1
        },
        {
          "col": "data",
          "idx": 1499645778000,
          "val": 1
        },
        {
          "col": "data",
          "idx": 1499645810000,
          "val": 1
        },
        {
          "col": "data",
          "idx": 1499645996000,
          "val": 1
        },
        {
          "col": "data",
          "idx": 1499646075000,
          "val": 1
        },
        {
          "col": "data",
          "idx": 1499646173000,
          "val": 1
        },
        {
          "col": "data",
          "idx": 1499646240000,
          "val": 1
        },
        {
          "col": "data",
          "idx": 1499646249000,
          "val": 1
        },
        {
          "col": "data",
          "idx": 1499646264000,
          "val": 1
        },
        {
          "col": "data",
          "idx": 1499646454000,
          "val": 1
        },
        {
          "col": "data",
          "idx": 1499646462000,
          "val": 1
        },
        {
          "col": "data",
          "idx": 1499646546000,
          "val": 1
        },
        {
          "col": "data",
          "idx": 1499646688000,
          "val": 1
        },
        {
          "col": "data",
          "idx": 1499646726000,
          "val": 1
        },
        {
          "col": "data",
          "idx": 1499646923000,
          "val": 1
        },
        {
          "col": "data",
          "idx": 1499646978000,
          "val": 1
        },
        {
          "col": "data",
          "idx": 1499647060000,
          "val": 1
        },
        {
          "col": "data",
          "idx": 1499647336000,
          "val": 1
        },
        {
          "col": "data",
          "idx": 1499647499000,
          "val": 1
        },
        {
          "col": "data",
          "idx": 1499648346000,
          "val": 1
        },
        {
          "col": "data",
          "idx": 1499648492000,
          "val": 1
        },
        {
          "col": "data",
          "idx": 1499648626000,
          "val": 1
        },
        {
          "col": "data",
          "idx": 1499648705000,
          "val": 1
        },
        {
          "col": "data",
          "idx": 1499648754000,
          "val": 1
        },
        {
          "col": "data",
          "idx": 1499648792000,
          "val": 1
        },
        {
          "col": "data",
          "idx": 1499648871000,
          "val": 1
        },
        {
          "col": "data",
          "idx": 1499649657000,
          "val": 1
        },
        {
          "col": "data",
          "idx": 1499649972000,
          "val": 1
        },
        {
          "col": "data",
          "idx": 1499650219000,
          "val": 1
        },
        {
          "col": "data",
          "idx": 1499650462000,
          "val": 1
        },
        {
          "col": "data",
          "idx": 1499650729000,
          "val": 1
        },
        {
          "col": "data",
          "idx": 1499651195000,
          "val": 1
        },
        {
          "col": "data",
          "idx": 1499651219000,
          "val": 1
        },
        {
          "col": "data",
          "idx": 1499651437000,
          "val": 1
        },
        {
          "col": "data",
          "idx": 1499651490000,
          "val": 1
        },
        {
          "col": "data",
          "idx": 1499652383000,
          "val": 1
        },
        {
          "col": "data",
          "idx": 1499653085000,
          "val": 1
        },
        {
          "col": "data",
          "idx": 1499653087000,
          "val": 1
        },
        {
          "col": "data",
          "idx": 1499653194000,
          "val": 1
        },
        {
          "col": "data",
          "idx": 1499653291000,
          "val": 1
        },
        {
          "col": "data",
          "idx": 1499653316000,
          "val": 1
        },
        {
          "col": "data",
          "idx": 1499653381000,
          "val": 1
        },
        {
          "col": "data",
          "idx": 1499653392000,
          "val": 1
        },
        {
          "col": "data",
          "idx": 1499653394000,
          "val": 1
        },
        {
          "col": "data",
          "idx": 1499654095000,
          "val": 1
        },
        {
          "col": "data",
          "idx": 1499654416000,
          "val": 1
        },
        {
          "col": "data",
          "idx": 1499654973000,
          "val": 1
        },
        {
          "col": "data",
          "idx": 1499654993000,
          "val": 1
        },
        {
          "col": "data",
          "idx": 1499655036000,
          "val": 1
        },
        {
          "col": "data",
          "idx": 1499655310000,
          "val": 1
        },
        {
          "col": "data",
          "idx": 1499655535000,
          "val": 1
        },
        {
          "col": "data",
          "idx": 1499655603000,
          "val": 1
        },
        {
          "col": "data",
          "idx": 1499655906000,
          "val": 1
        },
        {
          "col": "data",
          "idx": 1499656320000,
          "val": 1
        },
        {
          "col": "data",
          "idx": 1499656587000,
          "val": 1
        },
        {
          "col": "data",
          "idx": 1499656873000,
          "val": 1
        },
        {
          "col": "data",
          "idx": 1499656931000,
          "val": 1
        },
        {
          "col": "data",
          "idx": 1499657584000,
          "val": 1
        },
        {
          "col": "data",
          "idx": 1499657599000,
          "val": 1
        },
        {
          "col": "data",
          "idx": 1499657609000,
          "val": 1
        },
        {
          "col": "data",
          "idx": 1499658478000,
          "val": 1
        },
        {
          "col": "data",
          "idx": 1499660209000,
          "val": 1
        },
        {
          "col": "data",
          "idx": 1499660215000,
          "val": 1
        },
        {
          "col": "data",
          "idx": 1499662104000,
          "val": 1
        },
        {
          "col": "data",
          "idx": 1499662441000,
          "val": 1
        },
        {
          "col": "data",
          "idx": 1499662628000,
          "val": 1
        },
        {
          "col": "data",
          "idx": 1499662816000,
          "val": 1
        },
        {
          "col": "data",
          "idx": 1499662834000,
          "val": 1
        },
        {
          "col": "data",
          "idx": 1499663150000,
          "val": 1
        },
        {
          "col": "data",
          "idx": 1499663500000,
          "val": 1
        },
        {
          "col": "data",
          "idx": 1499663711000,
          "val": 1
        },
        {
          "col": "data",
          "idx": 1499663903000,
          "val": 1
        },
        {
          "col": "data",
          "idx": 1499663996000,
          "val": 1
        },
        {
          "col": "data",
          "idx": 1499664236000,
          "val": 1
        },
        {
          "col": "data",
          "idx": 1499664505000,
          "val": 1
        },
        {
          "col": "data",
          "idx": 1499664623000,
          "val": 1
        },
        {
          "col": "data",
          "idx": 1499665075000,
          "val": 1
        },
        {
          "col": "data",
          "idx": 1499665516000,
          "val": 1
        }
      ]
    }
  ],
  "height": 500,
  "legends": [],
  "marks": [
    {
      "from": {
        "data": "table",
        "transform": [
          {
            "keys": [
              "data.col"
            ],
            "type": "facet"
          }
        ]
      },
      "marks": [
        {
          "properties": {
            "enter": {
              "stroke": {
                "field": "data.col",
                "scale": "color"
              },
              "strokeWidth": {
                "value": 2
              },
              "x": {
                "field": "data.idx",
                "scale": "x"
              },
              "y": {
                "field": "data.val",
                "scale": "y"
              }
            }
          },
          "type": "line"
        }
      ],
      "type": "group"
    }
  ],
  "padding": "auto",
  "scales": [
    {
      "domain": {
        "data": "table",
        "field": "data.idx"
      },
      "name": "x",
      "range": "width",
      "type": "time"
    },
    {
      "domain": {
        "data": "table",
        "field": "data.val"
      },
      "name": "y",
      "nice": true,
      "range": "height"
    },
    {
      "domain": {
        "data": "table",
        "field": "data.col"
      },
      "name": "color",
      "range": "category20",
      "type": "ordinal"
    }
  ],
  "width": 960
}